midii/__init__.py
midii/config.py
midii/messages.py
midii/midifile.py
midii/note.py
midii/py.typed
midii/quantize.py
midii/test_midii.py
midii/utilities.py
midii/sample/__init__.py
midii/sample/dataset/SINGER_16_10TO29_CLEAR_FEMALE_BALLAD_C0632.mid
midii/sample/dataset/SINGER_66_30TO49_HUSKY_MALE_DANCE_C2835.mid
midii/sample/dataset/ba_05688_-4_a_s02_m_02.mid
midii/sample/dataset/ba_09303_+0_a_s02_m_02.mid
midii/sample/simple/test_sample1.mid
midii/sample/simple/test_sample2.mid
midii/sample/simple/test_sample3.mid
midii/sample/simple/test_sample4.mid
midii/sample/simple/test_sample5.mid
midii/sample/simple/test_sample6.mid
midii/sample/simple/test_sample7.mid
midii/sample/simple/test_sample8.mid
midii-0.1.41.dist-info/METADATA
midii-0.1.41.dist-info/WHEEL
midii-0.1.41.dist-info/licenses/LICENSE
midii-0.1.41.dist-info/RECORD
