Metadata-Version: 2.4
Name: midii
Version: 0.1.41
Summary: Midi Insights: midi analyzer
Project-URL: Repository, https://github.com/ccss17/midii
Author-email: ccss17 <chansol0505@naver.com>
License: MIT License
License-File: LICENSE
Requires-Python: >=3.10
Requires-Dist: mido>=1.3.0
Requires-Dist: numba>=0.60.0
Requires-Dist: numpy>=2.0.0
Requires-Dist: rich>=11.0.0
